{
  "info" : {
    "arguments" : [
      "devicectl",
      "device",
      "info",
      "apps",
      "--device",
      "8097F071-CAB6-5AF0-8258-BCD985E9D79E",
      "--json-output",
      "/Users/kenpan/「Projects」/life-os/docs/qa/evidence/kenos-ios-stability-2026-07-21/logs/doctor-apps.json"
    ],
    "commandType" : "devicectl.device.info.apps",
    "environment" : {

    },
    "jsonVersion" : 3,
    "outcome" : "success",
    "version" : "518.33"
  },
  "result" : {
    "apps" : [
      {
        "appClip" : false,
        "builtByDeveloper" : true,
        "bundleIdentifier" : "space.kenos.app.ios",
        "bundleVersion" : "202607220250",
        "defaultApp" : false,
        "hidden" : false,
        "internalApp" : false,
        "name" : "Kenos",
        "removable" : true,
        "url" : "file:///private/var/containers/Bundle/Application/CC1055D6-BEA8-4FFD-97CF-E19E17B45041/KenosIOS.app/",
        "version" : "1.0.0"
      },
      {
        "appClip" : false,
        "builtByDeveloper" : true,
        "bundleIdentifier" : "com.example.macremote.client",
        "bundleVersion" : "1",
        "defaultApp" : false,
        "hidden" : false,
        "internalApp" : false,
        "name" : "Mac Remote",
        "removable" : true,
        "url" : "file:///private/var/containers/Bundle/Application/6389DC9E-E755-4CD3-9515-70B53F98BD8A/Mac%20Remote.app/",
        "version" : "1.0"
      }
    ],
    "defaultAppsIncluded" : false,
    "deviceIdentifier" : "8097F071-CAB6-5AF0-8258-BCD985E9D79E",
    "hiddenAppsIncluded" : false,
    "internalAppsIncluded" : false,
    "removableAppsIncluded" : true
  }
}
